ondewo/__init__.py
ondewo/t2s/__init__.py
ondewo/t2s/text_to_speech_pb2.py
ondewo/t2s/text_to_speech_pb2.pyi
ondewo/t2s/text_to_speech_pb2_grpc.py
ondewo/t2s/client/__init__.py
ondewo/t2s/client/async_client.py
ondewo/t2s/client/async_services_container.py
ondewo/t2s/client/client.py
ondewo/t2s/client/client_config.py
ondewo/t2s/client/services_container.py
ondewo/t2s/client/services/__init__.py
ondewo/t2s/client/services/async_text_to_speech.py
ondewo/t2s/client/services/text_to_speech.py
ondewo_t2s_client-6.1.1.dist-info/LICENSE
ondewo_t2s_client-6.1.1.dist-info/METADATA
ondewo_t2s_client-6.1.1.dist-info/WHEEL
ondewo_t2s_client-6.1.1.dist-info/top_level.txt
ondewo_t2s_client-6.1.1.dist-info/RECORD
