Metadata-Version: 2.1
Name: ondewo-t2s-client
Version: 6.1.1
Summary: ONDEWO Text 2 Speech (T2S) Client library for Python
Home-page: https://github.com/ondewo/ondewo-t2s-client-python
Author: ONDEWO GmbH
Author-email: office@ondewo.com
Classifier: Development Status :: 5 - Production/Stable
Classifier: Intended Audience :: Developers
Classifier: License :: OSI Approved :: Apache Software License
Classifier: Operating System :: OS Independent
Classifier: Programming Language :: Python :: 3.8
Classifier: Programming Language :: Python :: 3.9
Classifier: Programming Language :: Python :: 3.10
Classifier: Programming Language :: Python :: 3.11
Classifier: Programming Language :: Python :: 3.12
Classifier: Topic :: Software Development :: Libraries
Requires-Python: >=3
License-File: LICENSE
Requires-Dist: cffi
Requires-Dist: google-api-core>=2.19.1
Requires-Dist: googleapis-common-protos>=1.63.2
Requires-Dist: grpcio-reflection>=1.65.5
Requires-Dist: grpcio-tools>=1.65.5
Requires-Dist: grpcio>=1.65.5
Requires-Dist: numpy
Requires-Dist: ondewo-client-utils>=3.1.0
Requires-Dist: polling>=0.3.2
Requires-Dist: protobuf>=5.27.3
Requires-Dist: regex>=2022.6.2
